Workbook

Sheet Costos Indirectos y Fijos
A2: Tipo de Pieza | B2: Descripción | C2: Unidad | D2: Cantidad | E2: Costo Mensual (COP) | F2: Costo Total (COP) | G2: Costo Total (USD)
B3: Luz | C3: Mes | D3: 2 | E3: 235000 | F3: =D3*E3 -> 470000 | G3: =F3/'Costo Directos'!$S$1 -> 117.5 | K3: Fundición | L3: 1850000
B4: Agua | C4: Mes | D4: 2 | E4: 35000 | F4: =D4*E4 -> 70000 | G4: =F4/'Costo Directos'!$S$1 -> 17.5 | L4: 250000
B5: fotografias y videos | C5: Mes | D5: 2 | E5: 1500000 | F5: =D5*E5 -> 3000000 | G5: =F5/'Costo Directos'!$S$1 -> 750 | L5: 350000
B6: Arriendo | C6: Mes | D6: 2 | E6: 300000 | F6: =D6*E6 -> 600000 | G6: =F6/'Costo Directos'!$S$1 -> 150 | L6: 175000
B7: Transporte | C7: Mes | D7: 2 | E7: 300000 | F7: =D7*E7 -> 600000 | G7: =F7/'Costo Directos'!$S$1 -> 150 | L7: =200*3600 -> 720000
B8: Herramientas (depreciación) | C8: Mes | D8: 2 | E8: 600000 | F8: =D8*E8 -> 1200000 | G8: =F8/'Costo Directos'!$S$1 -> 300 | K8: Total | L8: =SUM(L3:L7) -> 3345000
B9: Empaque | C9: Pieza | D9: 100 | E9: 3800 | F9: =D9*E9 -> 380000 | G9: =F9/'Costo Directos'!$S$1 -> 95
B10: Tarjetas | C10: Pieza | D10: 400 | E10: 950 | F10: =D10*E10 -> 380000 | G10: =F10/'Costo Directos'!$S$1 -> 95
B11: Ayudante | C11: 1 | D11: Total | F11: 800000 | G11: =F11/'Costo Directos'!$S$1 -> 200
B12: Alquiler de vitrinas | C12: 2 | D12: Total | F12: 253000 | G12: =F12/'Costo Directos'!$S$1 -> 63.25
B13: Acidos, Alcohol, Etc | D13: Total | F13: 600000 | G13: =F13/'Costo Directos'!$S$1 -> 150
B14: Resinas para moldes | D14: Total | F14: 2100000 | G14: =F14/'Costo Directos'!$S$1 -> 525
B15: Precio de Plata Total | C15: gramos | D15: 950 | E15: 4200 | F15: =D15*E15 -> 3990000 | G15: =F15/'Costo Directos'!$S$1 -> 997.5
B16: Fundición | F16: 3345000 | G16: =F16/'Costo Directos'!$S$1 -> 836.25
B17: costo etiquetas y imprimador por etiquetas | C17: total | D17: 1 | E17: 560000 | F17: =D17*E17 -> 560000 | G17: =F17/'Costo Directos'!$S$1 -> 140
B18: Costo de trabajo hora por 10mil | C18: hrs | D18: 750 | F18: =D18*10000 -> 7500000 | G18: =F18/'Costo Directos'!$S$1 -> 1875
B19: Total Costos Indirectos | F19: =SUM(F3:F18) -> 25848000 | G19: =SUM(G3:G18) -> 6462
B20: Gramos Total Salidos Despues de Trabajo | F20: 509
B21: Precio por Gramo Sin Ganancia | F21: =F19/F20 -> 50781.925 | G21: =F21/'Costo Directos'!$S$1 -> 12.695481
B22: Precio por Gramo Gramo con Ganancia | F22: =F21*15%+F21 -> 58399.214 | G22: =F22/'Costo Directos'!$S$1 -> 14.599804

Sheet Costo Directos
R1: Tipo de Cambio | S1: 4000
R2: PGC | S2: ='Costos Indirectos y Fijos'!F22 -> 58399.214 | U2: Piedra | V2: Precios Piedras
F3: Piedra 1 | I3: Piedra 2 | R3: Impuesto | S3: 0.19 | U3: Diamante | V3: 75000
A4: # de Pieza | B4: Nombre de Pieza | C4: Unidad | D4: Cantidad | E4: PCG | F4: Tipo | G4: Unidad | H4: Costo | I4: Tipo | J4: Unidad | K4: Costo | L4: Piedras Totales | M4: Esmalteo | N4: Unitario (COP) | O4: Impuesto | P4: Cadena | Q4: Total (COP) | R4: Total (USD) | U4: Esmeralda | V4: 38000
A5: 1 | B5: Hoja de Mapple Olive con Rubí | C5: Gramos | D5: 5.534 | E5: =D5*$S$2 -> 323181.25 | F5: Rubí | G5: 2 | H5: =VLOOKUP(F5,$U$2:$V$17,2,FALSE) -> 50000 | I5: No | L5: =(G5*H5)+(J5*K5) -> 100000 | M5: 50000 | N5: =E5+L5+M5 -> 473181.25 | O5: =N5+(N5*$S$3) -> 563085.69 | Q5: =O5+P5 -> 563085.69 | R5: =Q5/$S$1 -> 140.77142 | U5: Rubí | V5: 50000
A6: 2 | B6: Dije Bambú | C6: Gramos | D6: 1.87 | E6: =D6*$S$2 -> 109206.53 | F6: Citrino | G6: 2 | H6: =VLOOKUP(F6,$U$2:$V$17,2,FALSE) -> 25000 | I6: Amatista | J6: 3 | K6: =VLOOKUP(I6,$U$2:$V$17,2,FALSE) -> 25000 | L6: =(G6*H6)+(J6*K6) -> 125000 | M6: 50000 | N6: =E6+L6+M6 -> 284206.53 | O6: =N6+(N6*$S$3) -> 338205.77 | P6: 45000 | Q6: =O6+P6 -> 383205.77 | R6: =Q6/$S$1 -> 95.801443 | U6: Zafiro | V6: 50000
A7: 3 | B7: Aretes Transformers Mapple Rojo Con Esmeralda | C7: Gramos | D7: 5.712 | Q7: =Q8+Q9 -> 546895.81 | R7: =Q7/$S$1 -> 136.72395 | U7: Granate Verde | V7: 30000
A8: 3.1 | B8: Parte 1 Dijes | C8: Gramos | D8: 4.373 | E8: =D8*$S$2 -> 255379.76 | F8: Esmeralda | G8: 2 | H8: =VLOOKUP(F8,$U$2:$V$17,2,FALSE) -> 38000 | I8: No | L8: =(G8*H8)+(J8*K8) -> 76000 | M8: 50000 | N8: =E8+L8+M8 -> 381379.76 | O8: =N8+(N8*$S$3) -> 453841.92 | P8: 0 | Q8: =O8+P8 -> 453841.92 | R8: =Q8/$S$1 -> 113.46048 | U8: Acuamarina | V8: 45000
A9: 3.2 | B9: Parte 2 Aretes | C9: Gramos | D9: 1.339 | E9: =D9*$S$2 -> 78196.548 | F9: No | I9: No | L9: =(G9*H9)+(J9*K9) -> 0 | M9: 0 | N9: =E9+L9+M9 -> 78196.548 | O9: =N9+(N9*$S$3) -> 93053.892 | P9: 0 | Q9: =O9+P9 -> 93053.892 | R9: =Q9/$S$1 -> 23.263473 | U9: Zafiro Paparadga | V9: 100000
A10: 4 | B10: Dije Rojo Verde Mapple con 2 Zafiros | C10: Gramos | D10: 3.15 | E10: =D10*$S$2 -> 183957.52 | F10: Zafiro | G10: 2 | H10: =VLOOKUP(F10,$U$2:$V$17,2,FALSE) -> 50000 | I10: No | L10: =(G10*H10)+(J10*K10) -> 100000 | M10: 50000 | N10: =E10+L10+M10 -> 333957.52 | O10: =N10+(N10*$S$3) -> 397409.45 | P10: 45000 | Q10: =O10+P10 -> 442409.45 | R10: =Q10/$S$1 -> 110.60236 | U10: Granate Rojo | V10: 25000
A11: 5 | B11: Bambu Amarillo Verde Con Esmeralda | C11: Gramos | D11: 2.69 | E11: =D11*$S$2 -> 157093.89 | F11: Esmeralda | G11: 2 | H11: =VLOOKUP(F11,$U$2:$V$17,2,FALSE) -> 38000 | I11: No | L11: =(G11*H11)+(J11*K11) -> 76000 | M11: 50000 | N11: =E11+L11+M11 -> 283093.89 | O11: =N11+(N11*$S$3) -> 336881.72 | P11: 0 | Q11: =O11+P11 -> 336881.72 | R11: =Q11/$S$1 -> 84.220431 | U11: Amatista | V11: 25000
A12: 6 | B12: Bambu Verde 84 con Zafiros | C12: Gramos | D12: 3.059 | E12: =D12*$S$2 -> 178643.2 | F12: Zafiro | G12: 2 | H12: =VLOOKUP(F12,$U$2:$V$17,2,FALSE) -> 50000 | I12: No | L12: =(G12*H12)+(J12*K12) -> 100000 | M12: 50000 | N12: =E12+L12+M12 -> 328643.2 | O12: =N12+(N12*$S$3) -> 391085.4 | P12: 0 | Q12: =O12+P12 -> 391085.4 | R12: =Q12/$S$1 -> 97.771351 | U12: Citrino | V12: 25000
A13: 7 | B13: Broche Pensamientos con Zafiro Paparadga | C13: Gramos | D13: 10.344 | E13: =D13*$S$2 -> 604081.47 | F13: Zafiro Paparadga | G13: 1 | H13: =VLOOKUP(F13,$U$2:$V$17,2,FALSE) -> 100000 | L13: =(G13*H13)+(J13*K13) -> 100000 | M13: 50000 | N13: =E13+L13+M13 -> 754081.47 | O13: =N13+(N13*$S$3) -> 897356.95 | P13: 0 | Q13: =O13+P13 -> 897356.95 | R13: =Q13/$S$1 -> 224.33924 | U13: Peridoto | V13: 25000
A14: 8 | B14: Bambú Verde 83 con Esmeralda | C14: Gramos | D14: 1.91 | E14: =D14*$S$2 -> 111542.5 | F14: Esmeralda | G14: 2 | H14: =VLOOKUP(F14,$U$2:$V$17,2,FALSE) -> 38000 | L14: =(G14*H14)+(J14*K14) -> 76000 | M14: 50000 | N14: =E14+L14+M14 -> 237542.5 | O14: =N14+(N14*$S$3) -> 282675.57 | P14: 0 | Q14: =O14+P14 -> 282675.57 | R14: =Q14/$S$1 -> 70.668893 | U14: Tanzanita | V14: 35000
A15: 9 | B15: Bambú Azul Claro con Acuamarina | C15: Gramos | D15: 1.909 | E15: =D15*$S$2 -> 111484.1 | F15: Acuamarina | G15: 2 | H15: =VLOOKUP(F15,$U$2:$V$17,2,FALSE) -> 45000 | L15: =(G15*H15)+(J15*K15) -> 90000 | M15: 50000 | N15: =E15+L15+M15 -> 251484.1 | O15: =N15+(N15*$S$3) -> 299266.08 | P15: 0 | Q15: =O15+P15 -> 299266.08 | R15: =Q15/$S$1 -> 74.81652 | U15: CZ 1mm | V15: 300
A16: 10 | B16: Bambú Amatista con 2 Rubíes | C16: Gramos | D16: 3.1 | E16: =D16*$S$2 -> 181037.56 | F16: Rubí | G16: 2 | H16: =VLOOKUP(F16,$U$2:$V$17,2,FALSE) -> 50000 | L16: =(G16*H16)+(J16*K16) -> 100000 | M16: 50000 | N16: =E16+L16+M16 -> 331037.56 | O16: =N16+(N16*$S$3) -> 393934.7 | P16: 0 | Q16: =O16+P16 -> 393934.7 | R16: =Q16/$S$1 -> 98.483675 | U16: CZ | V16: 2000
A17: 11 | B17: Bambú Naranja con 2 Rubíes | C17: Gramos | D17: 1.929 | E17: =D17*$S$2 -> 112652.08 | F17: Rubí | G17: 2 | H17: =VLOOKUP(F17,$U$2:$V$17,2,FALSE) -> 50000 | L17: =(G17*H17)+(J17*K17) -> 100000 | M17: 50000 | N17: =E17+L17+M17 -> 262652.08 | O17: =N17+(N17*$S$3) -> 312555.98 | P17: 0 | Q17: =O17+P17 -> 312555.98 | R17: =Q17/$S$1 -> 78.138995 | U17: Corindon Laboratorio | V17: 2500
A18: 12 | B18: Bambú Amarillo con 2 Peridotos | C18: Gramos | D18: 3.23 | E18: =D18*$S$2 -> 188629.46 | F18: Peridoto | G18: 2 | H18: =VLOOKUP(F18,$U$2:$V$17,2,FALSE) -> 25000 | L18: =(G18*H18)+(J18*K18) -> 50000 | M18: 50000 | N18: =E18+L18+M18 -> 288629.46 | O18: =N18+(N18*$S$3) -> 343469.06 | P18: 0 | Q18: =O18+P18 -> 343469.06 | R18: =Q18/$S$1 -> 85.867265
A19: 13 | B19: Maple Hoja Naranja SM con 2 Esmeraldas | C19: Gramos | D19: 3.213 | E19: =D19*$S$2 -> 187636.68 | F19: Esmeralda | G19: 2 | H19: =VLOOKUP(F19,$U$2:$V$17,2,FALSE) -> 38000 | L19: =(G19*H19)+(J19*K19) -> 76000 | M19: 50000 | N19: =E19+L19+M19 -> 313636.68 | O19: =N19+(N19*$S$3) -> 373227.64 | P19: 0 | Q19: =O19+P19 -> 373227.64 | R19: =Q19/$S$1 -> 93.306911
A20: 14 | B20: Dije Bambú Verde 84 con 5 Rubíes | C20: Gramos | D20: 1.931 | E20: =D20*$S$2 -> 112768.88 | F20: Rubí | G20: 5 | H20: =VLOOKUP(F20,$U$2:$V$17,2,FALSE) -> 50000 | L20: =(G20*H20)+(J20*K20) -> 250000 | M20: 50000 | N20: =E20+L20+M20 -> 412768.88 | O20: =N20+(N20*$S$3) -> 491194.97 | P20: 45000 | Q20: =O20+P20 -> 536194.97 | R20: =Q20/$S$1 -> 134.04874
A21: 15 | B21: Dije Pensamiento Naranja con 4 Esmeraldas | C21: Gramos | D21: 2.449 | E21: =D21*$S$2 -> 143019.68 | F21: Esmeralda | G21: 4 | H21: =VLOOKUP(F21,$U$2:$V$17,2,FALSE) -> 38000 | L21: =(G21*H21)+(J21*K21) -> 152000 | M21: 50000 | N21: =E21+L21+M21 -> 345019.68 | O21: =N21+(N21*$S$3) -> 410573.41 | P21: 45000 | Q21: =O21+P21 -> 455573.41 | R21: =Q21/$S$1 -> 113.89335
A22: 16 | B22: Hoja Maple Color 83 con 2 Zafiros | C22: Gramos | D22: 5.69 | E22: =D22*$S$2 -> 332291.53 | F22: Zafiro | G22: 2 | H22: =VLOOKUP(F22,$U$2:$V$17,2,FALSE) -> 50000 | L22: =(G22*H22)+(J22*K22) -> 100000 | M22: 50000 | N22: =E22+L22+M22 -> 482291.53 | O22: =N22+(N22*$S$3) -> 573926.92 | P22: 0 | Q22: =O22+P22 -> 573926.92 | R22: =Q22/$S$1 -> 143.48173
A23: 17 | B23: Pensamiento Morado Amarillo con 2 Rubíes | C23: Gramos | D23: 4 | E23: =D23*$S$2 -> 233596.86 | F23: Rubí | G23: 2 | H23: =VLOOKUP(F23,$U$2:$V$17,2,FALSE) -> 50000 | L23: =(G23*H23)+(J23*K23) -> 100000 | M23: 50000 | N23: =E23+L23+M23 -> 383596.86 | O23: =N23+(N23*$S$3) -> 456480.26 | P23: 0 | Q23: =O23+P23 -> 456480.26 | R23: =Q23/$S$1 -> 114.12006
A24: 18 | B24: Maple Naranja Rosado con 2 Esmeraldas | C24: Gramos | D24: 7.444 | E24: =D24*$S$2 -> 434723.75 | F24: Esmeralda | G24: 2 | H24: =VLOOKUP(F24,$U$2:$V$17,2,FALSE) -> 38000 | L24: =(G24*H24)+(J24*K24) -> 76000 | M24: 50000 | N24: =E24+L24+M24 -> 560723.75 | O24: =N24+(N24*$S$3) -> 667261.26 | P24: 0 | Q24: =O24+P24 -> 667261.26 | R24: =Q24/$S$1 -> 166.81532
A25: 19 | B25: Mapple Verde Amarillo con 2 Granates | C25: Gramos | D25: 7.478 | E25: =D25*$S$2 -> 436709.32 | F25: Granate Rojo | G25: 2 | H25: =VLOOKUP(F25,$U$2:$V$17,2,FALSE) -> 25000 | L25: =(G25*H25)+(J25*K25) -> 50000 | M25: 50000 | N25: =E25+L25+M25 -> 536709.32 | O25: =N25+(N25*$S$3) -> 638684.09 | P25: 0 | Q25: =O25+P25 -> 638684.09 | R25: =Q25/$S$1 -> 159.67102
A26: 20 | B26: Pensamiento Azul Claro con 4 Zafiros Dije | C26: Gramos | D26: 2.417 | E26: =D26*$S$2 -> 141150.9 | F26: Zafiro | G26: 4 | H26: =VLOOKUP(F26,$U$2:$V$17,2,FALSE) -> 50000 | L26: =(G26*H26)+(J26*K26) -> 200000 | M26: 50000 | N26: =E26+L26+M26 -> 391150.9 | O26: =N26+(N26*$S$3) -> 465469.57 | P26: 45000 | Q26: =O26+P26 -> 510469.57 | R26: =Q26/$S$1 -> 127.61739
A27: 21 | B27: Orquidea Grande con Esmeralda 1 Kilate | C27: Gramos | E27: =D27*$S$2 -> 0 | H27: =VLOOKUP(F27,$U$2:$V$17,2,FALSE) -> #N/A | L27: =(G27*H27)+(J27*K27) -> #N/A | M27: 50000 | N27: =E27+L27+M27 -> #N/A | O27: =N27+(N27*$S$3) -> #N/A | P27: 0 | Q27: 2500000 | R27: =Q27/$S$1 -> 625
A28: 22 | B28: Pensamiento Morado con 2 Rubíes | C28: Gramos | D28: 3.956 | E28: =D28*$S$2 -> 231027.29 | F28: Rubí | G28: 2 | H28: =VLOOKUP(F28,$U$2:$V$17,2,FALSE) -> 50000 | L28: =(G28*H28)+(J28*K28) -> 100000 | M28: 50000 | N28: =E28+L28+M28 -> 381027.29 | O28: =N28+(N28*$S$3) -> 453422.48 | P28: 0 | Q28: =O28+P28 -> 453422.48 | R28: =Q28/$S$1 -> 113.35562
A29: 23 | B29: Pensamiento Rojo Amarillo con 2 Zafiros Rosados | C29: Gramos | D29: 4 | E29: =D29*$S$2 -> 233596.86 | F29: Zafiro | G29: 2 | H29: =VLOOKUP(F29,$U$2:$V$17,2,FALSE) -> 50000 | L29: =(G29*H29)+(J29*K29) -> 100000 | M29: 50000 | N29: =E29+L29+M29 -> 383596.86 | O29: =N29+(N29*$S$3) -> 456480.26 | P29: 0 | Q29: =O29+P29 -> 456480.26 | R29: =Q29/$S$1 -> 114.12006
A30: 24 | B30: Maple Hoja Roja con 2 Zafiros Amarillos | C30: Gramos | D30: 3.22 | E30: =D30*$S$2 -> 188045.47 | F30: Zafiro | G30: 2 | H30: =VLOOKUP(F30,$U$2:$V$17,2,FALSE) -> 50000 | L30: =(G30*H30)+(J30*K30) -> 100000 | M30: 50000 | N30: =E30+L30+M30 -> 338045.47 | O30: =N30+(N30*$S$3) -> 402274.11 | P30: 0 | Q30: =O30+P30 -> 402274.11 | R30: =Q30/$S$1 -> 100.56853
A31: 25 | B31: Pensamientos Amarillos con Tsavorita | C31: Gramos | D31: 4.327 | E31: =D31*$S$2 -> 252693.4 | F31: Zafiro | G31: 2 | H31: =VLOOKUP(F31,$U$2:$V$17,2,FALSE) -> 50000 | L31: =(G31*H31)+(J31*K31) -> 100000 | M31: 50000 | N31: =E31+L31+M31 -> 402693.4 | O31: =N31+(N31*$S$3) -> 479205.15 | P31: 0 | Q31: =O31+P31 -> 479205.15 | R31: =Q31/$S$1 -> 119.80129
A32: 26 | B32: Dije Morado con 4 Diamantes | C32: Gramos | D32: 2.417 | E32: =D32*$S$2 -> 141150.9 | F32: Diamante | G32: 4 | H32: =VLOOKUP(F32,$U$2:$V$17,2,FALSE) -> 75000 | L32: =(G32*H32)+(J32*K32) -> 300000 | M32: 50000 | N32: =E32+L32+M32 -> 491150.9 | O32: =N32+(N32*$S$3) -> 584469.57 | P32: 45000 | Q32: =O32+P32 -> 629469.57 | R32: =Q32/$S$1 -> 157.36739
A33: 27 | B33: Bambú Doble con 4 CZ y 8 Corindon | C33: Gramos | D33: 5.229 | E33: =D33*$S$2 -> 305369.49 | F33: CZ | G33: 4 | H33: =VLOOKUP(F33,$U$2:$V$17,2,FALSE) -> 2000 | I33: Corindon Laboratorio | J33: 8 | K33: =VLOOKUP(I33,$U$2:$V$17,2,FALSE) -> 2500 | L33: =(G33*H33)+(J33*K33) -> 28000 | M33: 50000 | N33: =E33+L33+M33 -> 383369.49 | O33: =N33+(N33*$S$3) -> 456209.69 | P33: 0 | Q33: =O33+P33 -> 456209.69 | R33: =Q33/$S$1 -> 114.05242
A34: 28 | B34: Manzanilla Blanca con Mariposas con 2CZ 8mm | C34: Gramos | D34: 11.397 | E34: =D34*$S$2 -> 665575.84 | F34: CZ | G34: 6 | H34: =VLOOKUP(F34,$U$2:$V$17,2,FALSE) -> 2000 | L34: =(G34*H34)+(J34*K34) -> 12000 | M34: 50000 | N34: =E34+L34+M34 -> 727575.84 | O34: =N34+(N34*$S$3) -> 865815.25 | P34: 0 | Q34: =O34+P34 -> 865815.25 | R34: =Q34/$S$1 -> 216.45381
A35: 29 | B35: Orquidea Roja Amarilla con 2 CZ Amarillo | C35: Gramos | D35: 5.316 | E35: =D35*$S$2 -> 310450.22 | F35: CZ | G35: 2 | H35: =VLOOKUP(F35,$U$2:$V$17,2,FALSE) -> 2000 | L35: =(G35*H35)+(J35*K35) -> 4000 | M35: 50000 | N35: =E35+L35+M35 -> 364450.22 | O35: =N35+(N35*$S$3) -> 433695.76 | P35: 0 | Q35: =O35+P35 -> 433695.76 | R35: =Q35/$S$1 -> 108.42394
A36: 30 | B36: Dije Maple Naranjo con 2 Esmeraldas | C36: Gramos | D36: 3.15 | E36: =D36*$S$2 -> 183957.52 | F36: Esmeralda | G36: 2 | H36: =VLOOKUP(F36,$U$2:$V$17,2,FALSE) -> 38000 | L36: =(G36*H36)+(J36*K36) -> 76000 | M36: 50000 | N36: =E36+L36+M36 -> 309957.52 | O36: =N36+(N36*$S$3) -> 368849.45 | P36: 45000 | Q36: =O36+P36 -> 413849.45 | R36: =Q36/$S$1 -> 103.46236
A37: 31 | B37: Maple Hoja 20a con 2 Esmeraldas | C37: Gramos | D37: 5.592 | E37: =D37*$S$2 -> 326568.41 | F37: Esmeralda | G37: 2 | H37: =VLOOKUP(F37,$U$2:$V$17,2,FALSE) -> 38000 | L37: =(G37*H37)+(J37*K37) -> 76000 | M37: 50000 | N37: =E37+L37+M37 -> 452568.41 | O37: =N37+(N37*$S$3) -> 538556.4 | P37: 0 | Q37: =O37+P37 -> 538556.4 | R37: =Q37/$S$1 -> 134.6391
A38: 32 | B38: Maple Hoja Verde 83 con 2 Zafiros | C38: Gramos | D38: 7.399 | E38: =D38*$S$2 -> 432095.79 | F38: Zafiro | G38: 2 | H38: =VLOOKUP(F38,$U$2:$V$17,2,FALSE) -> 50000 | L38: =(G38*H38)+(J38*K38) -> 100000 | M38: 50000 | N38: =E38+L38+M38 -> 582095.79 | O38: =N38+(N38*$S$3) -> 692693.98 | P38: 0 | Q38: =O38+P38 -> 692693.98 | R38: =Q38/$S$1 -> 173.1735
A39: 33 | B39: Aretes Transformers Mapple Verde Amarillo con 2 Zafiros | C39: Gramos | E39: =D39*$S$2 -> 0 | H39: =VLOOKUP(F39,$U$2:$V$17,2,FALSE) -> #N/A | L39: =(G39*H39)+(J39*K39) -> #N/A | M39: 50000 | N39: =E39+L39+M39 -> #N/A | O39: =N39+(N39*$S$3) -> #N/A | P39: 0 | Q39: =Q40+Q41 -> 627924.58 | R39: =Q39/$S$1 -> 156.98115
A40: 33.1 | B40: Parte 1 Dijes | C40: Gramos | D40: 4.244 | E40: =D40*$S$2 -> 247846.26 | F40: Zafiro | G40: 2 | H40: =VLOOKUP(F40,$U$2:$V$17,2,FALSE) -> 50000 | L40: =(G40*H40)+(J40*K40) -> 100000 | M40: 50000 | N40: =E40+L40+M40 -> 397846.26 | O40: =N40+(N40*$S$3) -> 473437.06 | P40: 0 | Q40: =O40+P40 -> 473437.06 | R40: =Q40/$S$1 -> 118.35926
A41: 33.2 | B41: Parte 2 Aretes | C41: Gramos | D41: 2.223 | E41: =D41*$S$2 -> 129821.45 | F41: No | I41: No | M41: 0 | N41: =E41+L41+M41 -> 129821.45 | O41: =N41+(N41*$S$3) -> 154487.53 | P41: 0 | Q41: =O41+P41 -> 154487.53 | R41: =Q41/$S$1 -> 38.621882
A42: 34 | B42: Aretes Transformers Pensamiento Blanco con CZ | C42: Gramos | E42: =D42*$S$2 -> 0 | H42: =VLOOKUP(F42,$U$2:$V$17,2,FALSE) -> #N/A | L42: =(G42*H42)+(J42*K42) -> #N/A | M42: 50000 | N42: =E42+L42+M42 -> #N/A | O42: =N42+(N42*$S$3) -> #N/A | P42: 0 | Q42: =Q43+Q44 -> 617336.06 | R42: =Q42/$S$1 -> 154.33402
A43: 34.1 | B43: Parte 1 Dijes | C43: Gramos | D43: 5.59 | E43: =D43*$S$2 -> 326451.61 | F43: CZ | G43: 4 | H43: =VLOOKUP(F43,$U$2:$V$17,2,FALSE) -> 2000 | L43: =(G43*H43)+(J43*K43) -> 8000 | M43: 50000 | N43: =E43+L43+M43 -> 384451.61 | O43: =N43+(N43*$S$3) -> 457497.41 | P43: 0 | Q43: =O43+P43 -> 457497.41 | R43: =Q43/$S$1 -> 114.37435
A44: 34.2 | B44: Parte 2 Aretes | C44: Gramos | D44: 2.3 | E44: =D44*$S$2 -> 134318.19 | F44: No | L44: =(G44*H44)+(J44*K44) -> 0 | M44: 0 | N44: =E44+L44+M44 -> 134318.19 | O44: =N44+(N44*$S$3) -> 159838.65 | P44: 0 | Q44: =O44+P44 -> 159838.65 | R44: =Q44/$S$1 -> 39.959662
A45: 35 | B45: Bambú Naranja con 6 CZ | C45: Gramos | D45: 2.556 | E45: =D45*$S$2 -> 149268.39 | F45: CZ | G45: 6 | H45: =VLOOKUP(F45,$U$2:$V$17,2,FALSE) -> 2000 | L45: =(G45*H45)+(J45*K45) -> 12000 | M45: 50000 | N45: =E45+L45+M45 -> 211268.39 | O45: =N45+(N45*$S$3) -> 251409.39 | P45: 0 | Q45: =O45+P45 -> 251409.39 | R45: =Q45/$S$1 -> 62.852346
A46: 36 | B46: Maple Hoja Color Café con 2 Rubíes | C46: Gramos | D46: 3.244 | E46: =D46*$S$2 -> 189447.05 | F46: Rubí | G46: 2 | H46: =VLOOKUP(F46,$U$2:$V$17,2,FALSE) -> 50000 | L46: =(G46*H46)+(J46*K46) -> 100000 | M46: 50000 | N46: =E46+L46+M46 -> 339447.05 | O46: =N46+(N46*$S$3) -> 403941.99 | P46: 0 | Q46: =O46+P46 -> 403941.99 | R46: =Q46/$S$1 -> 100.9855
A47: 37 | B47: Dije Landish Triple 9 CZ 1mm | C47: Gramos | D47: 3.175 | E47: =D47*$S$2 -> 185417.5 | F47: CZ 1mm | G47: 9 | H47: =VLOOKUP(F47,$U$2:$V$17,2,FALSE) -> 300 | L47: =(G47*H47)+(J47*K47) -> 2700 | M47: 70000 | N47: =E47+L47+M47 -> 258117.5 | O47: =N47+(N47*$S$3) -> 307159.83 | P47: 45000 | Q47: =O47+P47 -> 352159.83 | R47: =Q47/$S$1 -> 88.039958
A48: 38 | B48: Dije Landish Triple 9 CZ 1mm | C48: Gramos | D48: 3.175 | E48: =D48*$S$2 -> 185417.5 | F48: CZ 1mm | G48: 9 | H48: =VLOOKUP(F48,$U$2:$V$17,2,FALSE) -> 300 | L48: =(G48*H48)+(J48*K48) -> 2700 | M48: 70000 | N48: =E48+L48+M48 -> 258117.5 | O48: =N48+(N48*$S$3) -> 307159.83 | P48: 45000 | Q48: =O48+P48 -> 352159.83 | R48: =Q48/$S$1 -> 88.039958
A49: 39 | B49: Manzanilla Blanca con Mariposas con 2CZ 8mm | C49: Gramos | D49: 10.898 | E49: =D49*$S$2 -> 636434.64 | F49: CZ | G49: 6 | H49: =VLOOKUP(F49,$U$2:$V$17,2,FALSE) -> 2000 | L49: =(G49*H49)+(J49*K49) -> 12000 | M49: 50000 | N49: =E49+L49+M49 -> 698434.64 | O49: =N49+(N49*$S$3) -> 831137.22 | P49: 0 | Q49: =O49+P49 -> 831137.22 | R49: =Q49/$S$1 -> 207.7843
A50: 40 | B50: Manzanilla Blanca con Mariposas con 2CZ 8mm | C50: Gramos | D50: 11.294 | E50: =D50*$S$2 -> 659560.72 | F50: CZ | G50: 6 | H50: =VLOOKUP(F50,$U$2:$V$17,2,FALSE) -> 2000 | L50: =(G50*H50)+(J50*K50) -> 12000 | M50: 50000 | N50: =E50+L50+M50 -> 721560.72 | O50: =N50+(N50*$S$3) -> 858657.26 | P50: 0 | Q50: =O50+P50 -> 858657.26 | R50: =Q50/$S$1 -> 214.66432
A51: 41 | B51: Manzanilla Blanca con Mariposas con 2CZ 8mm | C51: Gramos | D51: 10.921 | E51: =D51*$S$2 -> 637777.82 | F51: CZ | G51: 6 | H51: =VLOOKUP(F51,$U$2:$V$17,2,FALSE) -> 2000 | L51: =(G51*H51)+(J51*K51) -> 12000 | M51: 50000 | N51: =E51+L51+M51 -> 699777.82 | O51: =N51+(N51*$S$3) -> 832735.6 | P51: 0 | Q51: =O51+P51 -> 832735.6 | R51: =Q51/$S$1 -> 208.1839
A52: 42 | B52: Orquidea Morada con 2 CZ Morados | C52: Gramos | D52: 5.256 | E52: =D52*$S$2 -> 306946.27 | F52: CZ | G52: 2 | H52: =VLOOKUP(F52,$U$2:$V$17,2,FALSE) -> 2000 | L52: =(G52*H52)+(J52*K52) -> 4000 | M52: 50000 | N52: =E52+L52+M52 -> 360946.27 | O52: =N52+(N52*$S$3) -> 429526.06 | P52: 0 | Q52: =O52+P52 -> 429526.06 | R52: =Q52/$S$1 -> 107.38152
A53: 43 | B53: Orquidea Blanca Amarilla con 2 CZ Verdes | C53: Gramos | D53: 5.184 | E53: =D53*$S$2 -> 302741.53 | F53: CZ | G53: 2 | H53: =VLOOKUP(F53,$U$2:$V$17,2,FALSE) -> 2000 | L53: =(G53*H53)+(J53*K53) -> 4000 | M53: 50000 | N53: =E53+L53+M53 -> 356741.53 | O53: =N53+(N53*$S$3) -> 424522.42 | P53: 0 | Q53: =O53+P53 -> 424522.42 | R53: =Q53/$S$1 -> 106.1306
A54: 44 | B54: Orquidea Transformer con 2 Rubíes Lab | C54: Gramos | E54: =D54*$S$2 -> 0 | H54: =VLOOKUP(F54,$U$2:$V$17,2,FALSE) -> #N/A | L54: =(G54*H54)+(J54*K54) -> #N/A | M54: 50000 | N54: =E54+L54+M54 -> #N/A | O54: =N54+(N54*$S$3) -> #N/A | P54: 0 | Q54: =Q55+Q56 -> 432661.92 | R54: =Q54/$S$1 -> 108.16548
A55: 44.1 | B55: Parte 1 Dijes | C55: Gramos | D55: 3.956 | E55: =D55*$S$2 -> 231027.29 | F55: Corindon Laboratorio | G55: 2 | H55: =VLOOKUP(F55,$U$2:$V$17,2,FALSE) -> 2500 | L55: =(G55*H55)+(J55*K55) -> 5000 | M55: 50000 | N55: =E55+L55+M55 -> 286027.29 | O55: =N55+(N55*$S$3) -> 340372.48 | P55: 0 | Q55: =O55+P55 -> 340372.48 | R55: =Q55/$S$1 -> 85.093119
A56: 44.2 | B56: Parte 2 Aretes | C56: Gramos | D56: 1.328 | E56: =D56*$S$2 -> 77554.156 | F56: No | L56: =(G56*H56)+(J56*K56) -> 0 | M56: 0 | N56: =E56+L56+M56 -> 77554.156 | O56: =N56+(N56*$S$3) -> 92289.446 | P56: 0 | Q56: =O56+P56 -> 92289.446 | R56: =Q56/$S$1 -> 23.072362
A57: 45 | B57: Orquidea Azul Transformer con 2 Rubíes Lab | C57: Gramos | E57: =D57*$S$2 -> 0 | L57: =(G57*H57)+(J57*K57) -> 0 | M57: 0 | N57: =E57+L57+M57 -> 0 | O57: =N57+(N57*$S$3) -> 0 | P57: 0 | Q57: =Q58+Q59 -> 434538.29 | R57: =Q57/$S$1 -> 108.63457
A58: 45.1 | B58: Parte 1 Dijes | C58: Gramos | D58: 3.884 | E58: =D58*$S$2 -> 226822.55 | F58: Corindon Laboratorio | G58: 2 | H58: =VLOOKUP(F58,$U$2:$V$17,2,FALSE) -> 2500 | L58: =(G58*H58)+(J58*K58) -> 5000 | M58: 50000 | N58: =E58+L58+M58 -> 281822.55 | O58: =N58+(N58*$S$3) -> 335368.83 | P58: 0 | Q58: =O58+P58 -> 335368.83 | R58: =Q58/$S$1 -> 83.842208
A59: 45.2 | B59: Parte 2 Aretes | C59: Gramos | D59: 1.427 | E59: =D59*$S$2 -> 83335.679 | F59: No | L59: =(G59*H59)+(J59*K59) -> 0 | M59: 0 | N59: =E59+L59+M59 -> 83335.679 | O59: =N59+(N59*$S$3) -> 99169.458 | P59: 0 | Q59: =O59+P59 -> 99169.458 | R59: =Q59/$S$1 -> 24.792364
A60: 46 | B60: Orquidea Azul Transformer con 2 Rubíes Lab | C60: Gramos | E60: =D60*$S$2 -> 0 | H60: =VLOOKUP(F60,$U$2:$V$17,2,FALSE) -> #N/A | L60: =(G60*H60)+(J60*K60) -> #N/A | M60: 50000 | N60: =E60+L60+M60 -> #N/A | O60: =N60+(N60*$S$3) -> #N/A | P60: 0 | Q60: =Q61+Q62 -> 441974.26 | R60: =Q60/$S$1 -> 110.49357
A61: 46.1 | B61: Parte 1 Dijes | C61: Gramos | D61: 3.988 | E61: =D61*$S$2 -> 232896.07 | F61: Corindon Laboratorio | G61: 2 | H61: =VLOOKUP(F61,$U$2:$V$17,2,FALSE) -> 2500 | L61: =(G61*H61)+(J61*K61) -> 5000 | M61: 50000 | N61: =E61+L61+M61 -> 287896.07 | O61: =N61+(N61*$S$3) -> 342596.32 | P61: 0 | Q61: =O61+P61 -> 342596.32 | R61: =Q61/$S$1 -> 85.64908
A62: 46.2 | B62: Parte 2 Aretes | C62: Gramos | D62: 1.43 | E62: =D62*$S$2 -> 83510.876 | F62: No | L62: =(G62*H62)+(J62*K62) -> 0 | M62: 0 | N62: =E62+L62+M62 -> 83510.876 | O62: =N62+(N62*$S$3) -> 99377.943 | P62: 0 | Q62: =O62+P62 -> 99377.943 | R62: =Q62/$S$1 -> 24.844486
A63: 47 | B63: Orquidea Azul Transformer con 2 Rubíes Lab | C63: Gramos | E63: =D63*$S$2 -> 0 | H63: =VLOOKUP(F63,$U$2:$V$17,2,FALSE) -> #N/A | L63: =(G63*H63)+(J63*K63) -> #N/A | M63: 50000 | N63: =E63+L63+M63 -> #N/A | O63: =N63+(N63*$S$3) -> #N/A | P63: 0 | Q63: =Q64+Q65 -> 428492.22 | R63: =Q63/$S$1 -> 107.12305
A64: 47.1 | B64: Parte 1 Dijes | C64: Gramos | D64: 3.801 | E64: =D64*$S$2 -> 221975.41 | F64: Corindon Laboratorio | G64: 2 | H64: =VLOOKUP(F64,$U$2:$V$17,2,FALSE) -> 2500 | L64: =(G64*H64)+(J64*K64) -> 5000 | M64: 50000 | N64: =E64+L64+M64 -> 276975.41 | O64: =N64+(N64*$S$3) -> 329600.74 | P64: 0 | Q64: =O64+P64 -> 329600.74 | R64: =Q64/$S$1 -> 82.400185
A65: 47.2 | B65: Parte 2 Aretes | C65: Gramos | D65: 1.423 | E65: =D65*$S$2 -> 83102.082 | F65: No | L65: =(G65*H65)+(J65*K65) -> 0 | M65: 0 | N65: =E65+L65+M65 -> 83102.082 | O65: =N65+(N65*$S$3) -> 98891.477 | P65: 0 | Q65: =O65+P65 -> 98891.477 | R65: =Q65/$S$1 -> 24.722869
A66: 48 | B66: Orquidea Blanco con Rojo con 2 CZ | C66: Gramos | D66: 5.426 | E66: =D66*$S$2 -> 316874.14 | F66: CZ | G66: 2 | H66: =VLOOKUP(F66,$U$2:$V$17,2,FALSE) -> 2000 | L66: =(G66*H66)+(J66*K66) -> 4000 | M66: 50000 | N66: =E66+L66+M66 -> 370874.14 | O66: =N66+(N66*$S$3) -> 441340.22 | P66: 0 | Q66: =O66+P66 -> 441340.22 | R66: =Q66/$S$1 -> 110.33506
A67: 49 | B67: Orquidea Blanco con Rojo con 2 CZ | C67: Gramos | D67: 5.181 | E67: =D67*$S$2 -> 302566.33 | F67: CZ | G67: 2 | H67: =VLOOKUP(F67,$U$2:$V$17,2,FALSE) -> 2000 | L67: =(G67*H67)+(J67*K67) -> 4000 | M67: 50000 | N67: =E67+L67+M67 -> 356566.33 | O67: =N67+(N67*$S$3) -> 424313.93 | P67: 0 | Q67: =O67+P67 -> 424313.93 | R67: =Q67/$S$1 -> 106.07848
A68: 50 | B68: Aretes Bamboo Doble Verde Morado con 10 Zafiros | C68: Gramos | D68: 4.753 | E68: =D68*$S$2 -> 277571.46 | F68: Corindon Laboratorio | G68: 10 | H68: =VLOOKUP(F68,$U$2:$V$17,2,FALSE) -> 2500 | I68: CZ | J68: 2 | K68: =VLOOKUP(I68,$U$2:$V$17,2,FALSE) -> 2000 | L68: =(G68*H68)+(J68*K68) -> 29000 | M68: 50000 | N68: =E68+L68+M68 -> 356571.46 | O68: =N68+(N68*$S$3) -> 424320.04 | P68: 0 | Q68: =O68+P68 -> 424320.04 | R68: =Q68/$S$1 -> 106.08001
A69: 51 | B69: Maple Hoja Roja con 2 Diamantes | C69: Gramos | D69: 5.655 | E69: =D69*$S$2 -> 330247.56 | F69: Diamante | G69: 2 | H69: =VLOOKUP(F69,$U$2:$V$17,2,FALSE) -> 75000 | L69: =(G69*H69)+(J69*K69) -> 150000 | M69: 50000 | N69: =E69+L69+M69 -> 530247.56 | O69: =N69+(N69*$S$3) -> 630994.59 | P69: 0 | Q69: =O69+P69 -> 630994.59 | R69: =Q69/$S$1 -> 157.74865
A70: 52 | B70: Semilla Maple con Esmalte de Vitraje | C70: Gramos | D70: 3.949 | E70: =D70*$S$2 -> 230618.5 | F70: No | L70: =(G70*H70)+(J70*K70) -> 0 | M70: 250000 | N70: =E70+L70+M70 -> 480618.5 | O70: =N70+(N70*$S$3) -> 571936.01 | P70: 0 | Q70: =O70+P70 -> 571936.01 | R70: =Q70/$S$1 -> 142.984
A71: 53 | B71: Maple Hoja Verde con 2 Diamantes | C71: Gramos | D71: 3.326 | E71: =D71*$S$2 -> 194235.79 | F71: Diamante | G71: 2 | H71: =VLOOKUP(F71,$U$2:$V$17,2,FALSE) -> 75000 | L71: =(G71*H71)+(J71*K71) -> 150000 | M71: 50000 | N71: =E71+L71+M71 -> 394235.79 | O71: =N71+(N71*$S$3) -> 469140.59 | P71: 0 | Q71: =O71+P71 -> 469140.59 | R71: =Q71/$S$1 -> 117.28515
A72: 54 | B72: Pensamiento Azul Claro con 2 Diamantes | C72: Gramos | D72: 4.097 | E72: =D72*$S$2 -> 239261.58 | F72: Diamante | G72: 2 | H72: =VLOOKUP(F72,$U$2:$V$17,2,FALSE) -> 75000 | L72: =(G72*H72)+(J72*K72) -> 150000 | M72: 50000 | N72: =E72+L72+M72 -> 439261.58 | O72: =N72+(N72*$S$3) -> 522721.28 | P72: 0 | Q72: =O72+P72 -> 522721.28 | R72: =Q72/$S$1 -> 130.68032
A73: 55 | B73: Pensamiento Morado con 2 Diamantes | C73: Gramos | D73: 4.89 | E73: =D73*$S$2 -> 285572.16 | F73: Diamante | G73: 2 | H73: =VLOOKUP(F73,$U$2:$V$17,2,FALSE) -> 75000 | L73: =(G73*H73)+(J73*K73) -> 150000 | M73: 50000 | N73: =E73+L73+M73 -> 485572.16 | O73: =N73+(N73*$S$3) -> 577830.87 | P73: 0 | Q73: =O73+P73 -> 577830.87 | R73: =Q73/$S$1 -> 144.45772
A74: 56 | B74: Transformer Pensamiento Azul con 4 Diamantes | C74: Gramos | E74: =D74*$S$2 -> 0 | L74: =(G74*H74)+(J74*K74) -> 0 | M74: 0 | N74: =E74+L74+M74 -> 0 | O74: =N74+(N74*$S$3) -> 0 | P74: 0 | Q74: =Q75+Q76 -> 735065.38 | R74: =Q74/$S$1 -> 183.76634
A75: 56.1 | B75: Parte 1 Dijes | C75: Gramos | D75: 3.185 | E75: =D75*$S$2 -> 186001.5 | F75: Diamante | G75: 4 | H75: =VLOOKUP(F75,$U$2:$V$17,2,FALSE) -> 75000 | L75: =(G75*H75)+(J75*K75) -> 300000 | M75: 50000 | N75: =E75+L75+M75 -> 536001.5 | O75: =N75+(N75*$S$3) -> 637841.78 | P75: 0 | Q75: =O75+P75 -> 637841.78 | R75: =Q75/$S$1 -> 159.46045
A76: 56.2 | B76: Parte 2 Aretes | C76: Gramos | D76: 1.399 | E76: =D76*$S$2 -> 81700.501 | F76: No | L76: =(G76*H76)+(J76*K76) -> 0 | M76: 0 | N76: =E76+L76+M76 -> 81700.501 | O76: =N76+(N76*$S$3) -> 97223.596 | P76: 0 | Q76: =O76+P76 -> 97223.596 | R76: =Q76/$S$1 -> 24.305899
A77: 57 | B77: Transformer Pensamiento Azul con 4 Diamantes | C77: Gramos | E77: =D77*$S$2 -> 0 | L77: =(G77*H77)+(J77*K77) -> 0 | M77: 0 | N77: =E77+L77+M77 -> 0 | O77: =N77+(N77*$S$3) -> 0 | P77: 0 | Q77: =Q78+Q79 -> 820057.84 | R77: =Q77/$S$1 -> 205.01446
A78: 57.1 | B78: Parte 1 Dijes | C78: Gramos | D78: 3.567 | E78: =D78*$S$2 -> 208310 | F78: Diamante | G78: 4 | H78: =VLOOKUP(F78,$U$2:$V$17,2,FALSE) -> 75000 | L78: =(G78*H78)+(J78*K78) -> 300000 | M78: 50000 | N78: =E78+L78+M78 -> 558310 | O78: =N78+(N78*$S$3) -> 664388.9 | P78: 0 | Q78: =O78+P78 -> 664388.9 | R78: =Q78/$S$1 -> 166.09722
A79: 57.2 | B79: Parte 2 Aretes | C79: Gramos | D79: 2.24 | E79: =D79*$S$2 -> 130814.24 | F79: No | L79: =(G79*H79)+(J79*K79) -> 0 | M79: 0 | N79: =E79+L79+M79 -> 130814.24 | O79: =N79+(N79*$S$3) -> 155668.95 | P79: 0 | Q79: =O79+P79 -> 155668.95 | R79: =Q79/$S$1 -> 38.917236
A80: 58 | B80: Bamboo Amarillo con CZ | C80: Gramos | D80: 1.245 | E80: =D80*$S$2 -> 72707.022 | F80: CZ | G80: 2 | H80: =VLOOKUP(F80,$U$2:$V$17,2,FALSE) -> 2000 | L80: =(G80*H80)+(J80*K80) -> 4000 | M80: 50000 | N80: =E80+L80+M80 -> 126707.02 | O80: =N80+(N80*$S$3) -> 150781.36 | P80: 0 | Q80: =O80+P80 -> 150781.36 | R80: =Q80/$S$1 -> 37.695339
A81: 59 | B81: Aretes Landish 18CZ | C81: Gramos | D81: 6.536 | E81: =D81*$S$2 -> 381697.26 | F81: CZ 1mm | G81: 18 | H81: =VLOOKUP(F81,$U$2:$V$17,2,FALSE) -> 300 | L81: =(G81*H81)+(J81*K81) -> 5400 | M81: 50000 | N81: =E81+L81+M81 -> 437097.26 | O81: =N81+(N81*$S$3) -> 520145.74 | P81: 0 | Q81: =O81+P81 -> 520145.74 | R81: =Q81/$S$1 -> 130.03644
A82: 60 | B82: Aretes Landish 18CZ | C82: Gramos | D82: 6.302 | E82: =D82*$S$2 -> 368031.85 | F82: CZ 1mm | G82: 18 | H82: =VLOOKUP(F82,$U$2:$V$17,2,FALSE) -> 300 | L82: =(G82*H82)+(J82*K82) -> 5400 | M82: 50000 | N82: =E82+L82+M82 -> 423431.85 | O82: =N82+(N82*$S$3) -> 503883.9 | P82: 0 | Q82: =O82+P82 -> 503883.9 | R82: =Q82/$S$1 -> 125.97097
A83: 61 | B83: Aretes Landish 18CZ | C83: Gramos | D83: 6.856 | E83: =D83*$S$2 -> 400385.01 | F83: CZ 1mm | G83: 18 | H83: =VLOOKUP(F83,$U$2:$V$17,2,FALSE) -> 300 | L83: =(G83*H83)+(J83*K83) -> 5400 | M83: 50000 | N83: =E83+L83+M83 -> 455785.01 | O83: =N83+(N83*$S$3) -> 542384.16 | P83: 0 | Q83: =O83+P83 -> 542384.16 | R83: =Q83/$S$1 -> 135.59604
A84: 62 | B84: Landish Largos 1 Tira | C84: Gramos | D84: 6.472 | E84: =D84*$S$2 -> 377959.71 | F84: CZ 1mm | G84: 18 | H84: =VLOOKUP(F84,$U$2:$V$17,2,FALSE) -> 300 | L84: =(G84*H84)+(J84*K84) -> 5400 | M84: 50000 | N84: =E84+L84+M84 -> 433359.71 | O84: =N84+(N84*$S$3) -> 515698.06 | P84: 0 | Q84: =O84+P84 -> 515698.06 | R84: =Q84/$S$1 -> 128.92451
A85: 63 | B85: Landish Largos 3 Tiras | C85: Gramos | D85: 8.803 | E85: =D85*$S$2 -> 514088.28 | F85: CZ 1mm | G85: 18 | H85: =VLOOKUP(F85,$U$2:$V$17,2,FALSE) -> 300 | L85: =(G85*H85)+(J85*K85) -> 5400 | M85: 50000 | N85: =E85+L85+M85 -> 569488.28 | O85: =N85+(N85*$S$3) -> 677691.06 | P85: 0 | Q85: =O85+P85 -> 677691.06 | R85: =Q85/$S$1 -> 169.42276
A86: 64 | B86: Anillo Pensamientos con 1 Diamante Azul Claro | C86: Gramos | D86: 5.854 | E86: =D86*$S$2 -> 341869 | F86: Diamante | G86: 1 | H86: =VLOOKUP(F86,$U$2:$V$17,2,FALSE) -> 75000 | L86: =(G86*H86)+(J86*K86) -> 75000 | M86: 50000 | N86: =E86+L86+M86 -> 466869 | O86: =N86+(N86*$S$3) -> 555574.11 | P86: 0 | Q86: =O86+P86 -> 555574.11 | R86: =Q86/$S$1 -> 138.89353
A87: 65 | B87: Anillo Pensamientos Blanco con CZ | C87: Gramos | D87: 6.89 | E87: =D87*$S$2 -> 402370.59 | F87: CZ | G87: 1 | H87: =VLOOKUP(F87,$U$2:$V$17,2,FALSE) -> 2000 | L87: =(G87*H87)+(J87*K87) -> 2000 | M87: 50000 | N87: =E87+L87+M87 -> 454370.59 | O87: =N87+(N87*$S$3) -> 540701 | P87: 0 | Q87: =O87+P87 -> 540701 | R87: =Q87/$S$1 -> 135.17525
A88: 66 | B88: Anillo Manzanilla con CZ 8mm | C88: Gramos | D88: 6.051 | E88: =D88*$S$2 -> 353373.64 | F88: CZ | G88: 3 | H88: =VLOOKUP(F88,$U$2:$V$17,2,FALSE) -> 2000 | L88: =(G88*H88)+(J88*K88) -> 6000 | M88: 50000 | N88: =E88+L88+M88 -> 409373.64 | O88: =N88+(N88*$S$3) -> 487154.64 | P88: 0 | Q88: =O88+P88 -> 487154.64 | R88: =Q88/$S$1 -> 121.78866
A89: 67 | B89: Anillo Pensamiento Amarillo Azul con Rubí | C89: Gramos | D89: 5.384 | E89: =D89*$S$2 -> 314421.37 | F89: Rubí | G89: 1 | H89: =VLOOKUP(F89,$U$2:$V$17,2,FALSE) -> 50000 | L89: =(G89*H89)+(J89*K89) -> 50000 | M89: 50000 | N89: =E89+L89+M89 -> 414421.37 | O89: =N89+(N89*$S$3) -> 493161.43 | P89: 0 | Q89: =O89+P89 -> 493161.43 | R89: =Q89/$S$1 -> 123.29036
A90: 68 | B90: Anillo Pensamiento Amarillo Con Esmeralda | C90: Gramos | D90: 6.902 | E90: =D90*$S$2 -> 403071.38 | F90: Esmeralda | G90: 1 | H90: =VLOOKUP(F90,$U$2:$V$17,2,FALSE) -> 38000 | L90: =(G90*H90)+(J90*K90) -> 38000 | M90: 50000 | N90: =E90+L90+M90 -> 491071.38 | O90: =N90+(N90*$S$3) -> 584374.94 | P90: 0 | Q90: =O90+P90 -> 584374.94 | R90: =Q90/$S$1 -> 146.09373
A91: 69 | B91: Anillo Pensamiento Rojo con Zafiro | C91: Gramos | D91: 6.105 | E91: =D91*$S$2 -> 356527.2 | F91: Zafiro | G91: 1 | H91: =VLOOKUP(F91,$U$2:$V$17,2,FALSE) -> 50000 | L91: =(G91*H91)+(J91*K91) -> 50000 | M91: 50000 | N91: =E91+L91+M91 -> 456527.2 | O91: =N91+(N91*$S$3) -> 543267.37 | P91: 0 | Q91: =O91+P91 -> 543267.37 | R91: =Q91/$S$1 -> 135.81684
... A110: 88 | B110: Maple Hoja Amarillo Naranja con 2 Esmeraldas | C110: Gramos | D110: 5.241 | E110: =D110*$S$2 -> 306070.28 | F110: Esmeralda | G110: 2 | H110: =VLOOKUP(F110,$U$2:$V$17,2,FALSE) -> 38000 | L110: =(G110*H110)+(J110*K110) -> 76000 | M110: 50000 | N110: =E110+L110+M110 -> 432070.28 | O110: =N110+(N110*$S$3) -> 514163.63 | P110: 0 | Q110: =O110+P110 -> 514163.63 | R110: =Q110/$S$1 -> 128.54091
A111: 89 | B111: Cadena | C111: Gramos | E111: =D111*$S$2 -> 0 | L111: =(G111*H111)+(J111*K111) -> 0 | M111: 0 | N111: =E111+L111+M111 -> 0 | O111: =N111+(N111*$S$3) -> 0 | P111: 45000 | Q111: =O111+P111 -> 45000 | R111: =Q111/$S$1 -> 11.25
A112: 90 | B112: Cadena | C112: Gramos | E112: =D112*$S$2 -> 0 | L112: =(G112*H112)+(J112*K112) -> 0 | M112: 0 | N112: =E112+L112+M112 -> 0 | O112: =N112+(N112*$S$3) -> 0 | P112: 45000 | Q112: =O112+P112 -> 45000 | R112: =Q112/$S$1 -> 11.25
A113: 91 | B113: Cadena | C113: Gramos | E113: =D113*$S$2 -> 0 | L113: =(G113*H113)+(J113*K113) -> 0 | M113: 0 | N113: =E113+L113+M113 -> 0 | O113: =N113+(N113*$S$3) -> 0 | P113: 45000 | Q113: =O113+P113 -> 45000 | R113: =Q113/$S$1 -> 11.25
A114: 92 | B114: Cadena | C114: Gramos | E114: =D114*$S$2 -> 0 | L114: =(G114*H114)+(J114*K114) -> 0 | M114: 0 | N114: =E114+L114+M114 -> 0 | O114: =N114+(N114*$S$3) -> 0 | P114: 45000 | Q114: =O114+P114 -> 45000 | R114: =Q114/$S$1 -> 11.25
A115: 93 | B115: Aretes Base | C115: Gramos | D115: 2.281 | E115: =D115*$S$2 -> 133208.61 | F115: No | L115: =(G115*H115)+(J115*K115) -> 0 | M115: 0 | N115: =E115+L115+M115 -> 133208.61 | O115: =N115+(N115*$S$3) -> 158518.24 | P115: 0 | Q115: =O115+P115 -> 158518.24 | R115: =Q115/$S$1 -> 39.629561

Sheet Costos Total
A1: Tipo de Pieza | B1: Descripción | C1: Costo (COP) | D1: Costo (USD)
B2: Costos Directos
B3: Costos Indirectos
B4: Costo Total de Producción

Sheet Sheet4
C2: peso de compra | D2: peso de salida
B3: Precio metal Gramo de Compra
